seafileapi/__init__.py
seafileapi/exceptions.py
seafileapi/main.py
seafileapi/utils.py
seafileapi2-2.0.1.dist-info/LICENSE
seafileapi2-2.0.1.dist-info/METADATA
seafileapi2-2.0.1.dist-info/WHEEL
seafileapi2-2.0.1.dist-info/top_level.txt
seafileapi2-2.0.1.dist-info/RECORD
