Metadata-Version: 2.1
Name: seafileapi2
Version: 2.0.1
Summary: Python client for Seafile Web API
Home-page: https://github.com/haiwen/python-seafile
Author: seafile
Author-email: support@seafile.com
License: BSD
Platform: any
Classifier: Programming Language :: Python
Requires-Dist: requests
